{"nodes": [{"id": "prd_02_roles", "label": "User Roles & Permissions", "file_type": "document", "source_file": "docs/prd/02-roles.md", "source_location": null, "source_url": null, "captured_at": null, "author": null, "contributor": null}, {"id": "concept_role_admin", "label": "Role: Admin", "file_type": "document", "source_file": "docs/prd/02-roles.md", "source_location": null, "source_url": null, "captured_at": null, "author": null, "contributor": null}, {"id": "concept_role_kasir", "label": "Role: Kasir", "file_type": "document", "source_file": "docs/prd/02-roles.md", "source_location": null, "source_url": null, "captured_at": null, "author": null, "contributor": null}, {"id": "concept_rbac", "label": "RBAC (Role-Based Access Control)", "file_type": "document", "source_file": "docs/prd/02-roles.md", "source_location": null, "source_url": null, "captured_at": null, "author": null, "contributor": null}], "edges": [{"source": "prd_02_roles", "target": "concept_role_admin", "relation": "references", "confidence": "EXTRACTED", "confidence_score": 1.0, "source_file": "docs/prd/02-roles.md", "source_location": "Role table", "weight": 1.0}, {"source": "prd_02_roles", "target": "concept_role_kasir", "relation": "references", "confidence": "EXTRACTED", "confidence_score": 1.0, "source_file": "docs/prd/02-roles.md", "source_location": "Role table", "weight": 1.0}, {"source": "prd_02_roles", "target": "concept_rbac", "relation": "references", "confidence": "EXTRACTED", "confidence_score": 1.0, "source_file": "docs/prd/02-roles.md", "source_location": "Footer note", "weight": 1.0}, {"source": "concept_role_admin", "target": "concept_rbac", "relation": "conceptually_related_to", "confidence": "EXTRACTED", "confidence_score": 1.0, "source_file": "docs/prd/02-roles.md", "source_location": "RBAC note", "weight": 1.0}, {"source": "concept_role_kasir", "target": "concept_rbac", "relation": "conceptually_related_to", "confidence": "EXTRACTED", "confidence_score": 1.0, "source_file": "docs/prd/02-roles.md", "source_location": "RBAC note", "weight": 1.0}], "hyperedges": [{"id": "rbac_roles", "label": "RBAC Role System (Admin + Kasir)", "nodes": ["concept_role_admin", "concept_role_kasir", "concept_rbac", "prd_02_roles"], "relation": "implement", "confidence": "EXTRACTED", "confidence_score": 1.0, "source_file": "docs/prd/02-roles.md"}]}